tpsp/__init__.py
tpsp-1.0.1.dist-info/LICENSE
tpsp-1.0.1.dist-info/METADATA
tpsp-1.0.1.dist-info/WHEEL
tpsp-1.0.1.dist-info/entry_points.txt
tpsp-1.0.1.dist-info/top_level.txt
tpsp-1.0.1.dist-info/RECORD
