Metadata-Version: 2.1
Name: tpsp
Version: 1.0.1
Summary: CLI to CPTM and Metro lines status
Home-page: https://github.com/caian-org/tpsp
Author: Caian R. Ertl
Author-email: hi@caian.org
License: CC0
Platform: UNKNOWN
Classifier: Environment :: Console
Classifier: Programming Language :: Python
Classifier: Programming Language :: Python :: 3.6
Classifier: Programming Language :: Python :: 3.7
Classifier: Programming Language :: Python :: 3.8
Classifier: Programming Language :: Python :: 3.9
Classifier: Programming Language :: Python :: 3.10
Requires-Python: >=3.6.1
License-File: LICENSE
Requires-Dist: appdirs (==1.4.4)
Requires-Dist: bs4 (==0.0.1)
Requires-Dist: certifi (==2021.10.8)
Requires-Dist: colorama (==0.4.4)
Requires-Dist: fake-useragent (==0.1.11)
Requires-Dist: parse (==1.19.0)
Requires-Dist: pyee (==8.2.2)
Requires-Dist: pyquery (==1.4.3)
Requires-Dist: requests-html (==0.10.0)
Requires-Dist: tabulate (==0.8.9)
Requires-Dist: w3lib (==1.22.0)
Requires-Dist: websockets (==9.1) ; python_full_version >= "3.6.1"
Requires-Dist: pyppeteer (==0.2.6) ; python_full_version >= "3.6.1" and python_version < "4"
Requires-Dist: six (==1.16.0) ; python_version >= "2.7" and python_version not in "3.0, 3.1, 3.2"
Requires-Dist: cssselect (==1.1.0) ; python_version >= "2.7" and python_version not in "3.0, 3.1, 3.2, 3.3"
Requires-Dist: tqdm (==4.62.3) ; python_version >= "2.7" and python_version not in "3.0, 3.1, 3.2, 3.3"
Requires-Dist: lxml (==4.6.4) ; python_version >= "2.7" and python_version not in "3.0, 3.1, 3.2, 3.3, 3.4"
Requires-Dist: urllib3 (==1.26.7) ; python_version >= "2.7" and python_version not in "3.0, 3.1, 3.2, 3.3, 3.4" and python_version < "4"
Requires-Dist: requests (==2.26.0) ; python_version >= "2.7" and python_version not in "3.0, 3.1, 3.2, 3.3, 3.4, 3.5"
Requires-Dist: charset-normalizer (==2.0.7) ; python_version >= "3"
Requires-Dist: idna (==3.3) ; python_version >= "3"
Requires-Dist: beautifulsoup4 (==4.10.0) ; python_version >= "3.1"
Requires-Dist: importlib-metadata (==4.8.2) ; python_version >= "3.6"
Requires-Dist: soupsieve (==2.3) ; python_version >= "3.6"
Requires-Dist: zipp (==3.6.0) ; python_version >= "3.6"
